{"id":280380,"name":"七つの大罪 神々の逆鱗","name_cn":"七大罪 诸神的逆鳞","type":"动画","image":"6e/b8/280380_232Z9.jpg","link":"https://bgm.tv/subject/280380","eps":24,"collection":{"on_hold":145,"dropped":281,"wish":245,"collect":1610,"doing":167},"date":"2019-10-09","summary":"いまだ人と、人ならざるものの世界が、分かたれてはいなかった古の物語。\r\n三千年の時を経て復活した、魔神族の精鋭〈十戒〉との戦いに 〈七つの大罪〉は敗れ、メリオダスは死んだ。\r\nそして、ブリタニアには暗黒の時代が訪れる。\r\nディアンヌ、キング、ゴウセルも行方不明の中、リオネス王国に迫る〈十戒〉の魔の手。\r\nエスカノールがエスタロッサを退けるも劣勢は続く。\r\nそして、エリザベスが窮地に陥ったその時、圧倒的な力を取り戻したメリオダスが煉獄より復活を果たす。\r\n〈十戒〉のグレイロードとフラウドリンは討たれリオネス王国は守られた。\r\n復旧する建物。しかし、人々の恐怖に傷ついた心は癒えない。\r\nそして、力を取り戻した事でメリオダスは 最凶の魔神と呼ばれた時代に逆行しつつあった。\r\nキャメロット王国を根城にする〈十戒〉の脅威は続く。\r\nブリタニアを魔神族から解放する為、〈七つの大罪〉は再集結に向けて動き出すー。","rating":{"rank":9032,"total":1079,"count":{"1":30,"2":62,"3":147,"4":264,"5":252,"6":207,"7":68,"8":31,"9":5,"10":13},"score":4.7},"updated_at":"2025-04-13T23:11:28+08:00"}