{"id":295017,"name":"回復術士のやり直し","name_cn":"回复术士的重来人生","type":"动画","image":"c7/3f/295017_90As6.jpg","link":"https://bgm.tv/subject/295017","eps":12,"collection":{"on_hold":383,"dropped":661,"wish":1116,"collect":15471,"doing":786},"date":"2021-01-13","summary":"觉醒了“愈”之勇者的素质，开始与勇者们一同踏上拯救世界冒险之旅的少年·克亚路。\r\n然而，身为没有战斗能力的回复术士，等待着他的是能力遭到勇者们榨取，饱受虐待的每一天。\r\n自由和尊严被剥夺，连自我都快要失去的克亚路，某天恢复了理智，并抵达了“回复“的真实。\r\n“回复“并非仅仅是治愈。“回复“是从根源动摇世界与人类的力量。\r\n克亚路“回复“了世界本身，下定决心从四年前开始“重启”一切。并且，他也为能报复勇者们而激动不已……\r\n“来吧，派对（复仇）要开始了——”","rating":{"rank":6451,"total":9696,"count":{"1":93,"2":106,"3":181,"4":474,"5":1579,"6":3296,"7":2459,"8":987,"9":205,"10":316},"score":6.2},"updated_at":"2025-04-13T22:46:08+08:00"}