{"id":479922,"name":"ニートくノ一となぜか同棲はじめました","name_cn":"我家有个阿宅女忍者","type":"动画","image":"8e/1a/479922_xqtl0.jpg","link":"https://bgm.tv/subject/479922","eps":24,"collection":{"on_hold":141,"dropped":487,"wish":426,"collect":606,"doing":933},"date":"2025-01-04","summary":"平凡なサラリーマン・安海政あつみつかさを妖魔から守護するべく、居候を条件に主従契約を結んだ天才くノ一・出浦白津莉いでうらしづり。\r\n颯爽と妖魔を倒す姿とは裏腹に、しづりはゲーム三昧のオタクニートであった。\r\n政に甘やかされ、ぐうたら同棲生活を送るしづりのもとにクセつよくノ一たちも集結し…。\r\nオタクでニートな天才くノ一との同棲ラブコメ！","rating":{"rank":8893,"total":800,"count":{"1":13,"2":15,"3":56,"4":161,"5":275,"6":214,"7":57,"8":2,"9":3,"10":4},"score":5},"updated_at":"2025-04-13T22:22:16+08:00"}